<?xml version="1.0"?>
<!--
/**
 * Brander_ShopReview extension
 * 
 * NOTICE OF LICENSE
 * 
 * This source file is subject to the MIT License
 * that is bundled with this package in the file LICENSE.txt.
 * It is also available through the world-wide-web at this URL:
 * http://opensource.org/licenses/mit-license.php
 * 
 * @category   	Brander
 * @package		Brander_ShopReview
 * @copyright  	Copyright (c) 2016
 * @license		http://opensource.org/licenses/mit-license.php MIT License
 */
-->
<config>
    <acl>
        <resources>
            <admin>
                <children>
                    <system>
                        <children>
                            <config>
                                <children>
                                    <brander_shopreview translate="title" module="brander_shopreview">
                                        <title>ShopReview</title>
                                    </brander_shopreview>
                                </children>
                            </config>
                        </children>
                    </system>
                    <system>
                        <children>
                            <brander_shopreview translate="title" module="brander_shopreview">
                                <title>Shop Review</title>
                                <children>
                                    <shopreview translate="title" module="brander_shopreview">
                                        <title>Shop Review</title>
                                        <sort_order>0</sort_order>
                                    </shopreview>
                                </children>
                            </brander_shopreview>                        </children>
                    </system>

                </children>
            </admin>
        </resources>
    </acl>
    <menu>
        <system>
            <children>
                <brander_shopreview translate="title" module="brander_shopreview">
                    <title>Shop Review</title>
                    <sort_order>0</sort_order>
                    <children>
                        <shopreview translate="title" module="brander_shopreview">
                            <title>Shop Review</title>
                            <action>adminhtml/shopreview_shopreview</action>
                            <sort_order>0</sort_order>
                        </shopreview>
                    </children>
                </brander_shopreview>            </children>
        </system>

    </menu>
</config>
